django_markdown_html_field/__init__.py
django_markdown_html_field/fields.py
django_markdown_html_field/sanitizer.py
django_markdown_html_field/worker.py
django_markdown_html_field/extensions/__init__.py
django_markdown_html_field/extensions/super_sub_script.py
django_markdown_html_field/extensions/video.py
django_markdown_html_field-1.0.1.dist-info/licenses/LICENSE
django_markdown_html_field-1.0.1.dist-info/METADATA
django_markdown_html_field-1.0.1.dist-info/WHEEL
django_markdown_html_field-1.0.1.dist-info/top_level.txt
django_markdown_html_field-1.0.1.dist-info/RECORD
