Metadata-Version: 2.4
Name: django-markdown-html-field
Version: 1.0.1
Summary: Django Markdown to HTML Field
Author-email: Evgenii Legotckoi <evgenii.legotckoi@gmail.com>
License: MIT
Classifier: Framework :: Django
Classifier: Framework :: Django :: 4.2
Classifier: Framework :: Django :: 5
Classifier: Framework :: Django :: 6
Classifier: Topic :: Text Processing :: Markup
Classifier: Topic :: Text Processing :: Markup :: Markdown
Classifier: Topic :: Text Processing :: Markup :: HTML
Classifier: Programming Language :: Python :: 3.10
Classifier: License :: OSI Approved :: MIT License
Requires-Python: >=3.10
License-File: LICENSE
Requires-Dist: django>=4.2
Requires-Dist: markdown>=3.9
Requires-Dist: beautifulsoup4>=4.12
Requires-Dist: lxml>=4.6.3
Requires-Dist: python-slugify>=8.0.4
Dynamic: license-file
